mcp_server_xfetch/__init__.py
mcp_server_xfetch/__main__.py
mcp_server_xfetch/server.py
mcp_server_xfetch-0.1.1.dist-info/METADATA
mcp_server_xfetch-0.1.1.dist-info/WHEEL
mcp_server_xfetch-0.1.1.dist-info/entry_points.txt
mcp_server_xfetch-0.1.1.dist-info/licenses/LICENSE
mcp_server_xfetch-0.1.1.dist-info/RECORD
