Metadata-Version: 2.4
Name: mcp-server-xfetch
Version: 0.1.1
Summary: Enhanced MCP fetch server (fetch on steroids) that works through xfetch.ai service. Unlocks access to websites blocked by Cloudflare and other protection systems that regular fetch can't handle.
Project-URL: Homepage, https://xfetch.ai
Project-URL: Documentation, https://xfetch.ai
Project-URL: Repository, https://github.com/xfetchai/mcp-server-xfetch
Author-email: XFetch Team <xfetchai@gmail.com>
Maintainer-email: XFetch Team <xfetchai@gmail.com>
License: MIT
License-File: LICENSE
Keywords: automation,bypass,cloudflare,http,javascript-rendering,llm,mcp,web-scraping
Classifier: Development Status :: 4 - Beta
Classifier: Intended Audience :: Developers
Classifier: License :: OSI Approved :: MIT License
Classifier: Programming Language :: Python :: 3
Classifier: Programming Language :: Python :: 3.10
Classifier: Topic :: Internet :: WWW/HTTP
Classifier: Topic :: Internet :: WWW/HTTP :: Dynamic Content
Classifier: Topic :: Software Development :: Libraries :: Python Modules
Requires-Python: >=3.10
Requires-Dist: httpx<0.28
Requires-Dist: markdownify>=0.13.1
Requires-Dist: mcp>=1.6.0
Requires-Dist: parsel>=1.10.0
Requires-Dist: protego>=0.3.1
Requires-Dist: pydantic>=2.0.0
Requires-Dist: readabilipy>=0.2.0
Requires-Dist: requests>=2.32.3
